VASP2KP/__init__.py
VASP2KP/_get_kp_Zeeman.py
VASP2KP/_numeric_kp.py
VASP2KP/_read_data.py
VASP2KP/_standard_kp.py
VASP2KP/_transform_matrix.py
VASP2KP-1.1.5.dist-info/LICENSE.txt
VASP2KP-1.1.5.dist-info/METADATA
VASP2KP-1.1.5.dist-info/WHEEL
VASP2KP-1.1.5.dist-info/top_level.txt
VASP2KP-1.1.5.dist-info/RECORD
